nopecha_extension/__init__.py
nopecha_extension/patcher.py
nopecha_extension-0.0.2.dist-info/METADATA
nopecha_extension-0.0.2.dist-info/WHEEL
nopecha_extension-0.0.2.dist-info/top_level.txt
nopecha_extension-0.0.2.dist-info/RECORD
