Metadata-Version: 2.4
Name: nopecha-extension
Version: 0.0.2
Summary: Automated CAPTCHA solver for your browser USING THE EXTENSION. Works with Selenium, Puppeteer, Playwright, and more.
Author: 4EYES
Author-email: 4EYES <erererer1967@gmail.com>
Requires-Python: >=3.7
Requires-Dist: chrome_extension_python>=1.0.0
Dynamic: author
Dynamic: requires-python
